HISTORY.md
MANIFEST.in
README.md
requirements.txt
setup.cfg
setup.py
versioneer.py
track_changes/__init__.py
track_changes/_version.py
track_changes/utils.py
track_changes.egg-info/PKG-INFO
track_changes.egg-info/SOURCES.txt
track_changes.egg-info/dependency_links.txt
track_changes.egg-info/entry_points.txt
track_changes.egg-info/not-zip-safe
track_changes.egg-info/requires.txt
track_changes.egg-info/top_level.txt
track_changes/resources/__init__.py
track_changes/resources/changelog_template.md