Metadata-Version: 2.1
Name: track-changes
Version: 0.8
Summary: Project Short Description
Home-page: http://zhipengx.com/
Author: xzpjerry
Author-email: xzpjerry@gmail.com
License: UNKNOWN
Keywords: track_changes
Platform: UNKNOWN
Classifier: Programming Language :: Python :: 3
Classifier: Programming Language :: Python :: 3.6
Classifier: Programming Language :: Python :: 3.7
Classifier: Programming Language :: Python :: 3.8
Classifier: Intended Audience :: Developers
Classifier: Operating System :: OS Independent
Classifier: Environment :: Console
Requires-Python: >=3.6
